topsis_dipesh_jindal_101803686/__init__.py
TOPSIS_Dipesh_101803686-0.1.dist-info/LICENSE
TOPSIS_Dipesh_101803686-0.1.dist-info/METADATA
TOPSIS_Dipesh_101803686-0.1.dist-info/WHEEL
TOPSIS_Dipesh_101803686-0.1.dist-info/top_level.txt
TOPSIS_Dipesh_101803686-0.1.dist-info/RECORD
