Metadata-Version: 2.1
Name: TOPSIS-Dipesh-101803686
Version: 0.1
Summary: Package for calculating Topsis Score
Home-page: UNKNOWN
Author: Dipesh Jindal
License: MIT
Platform: UNKNOWN
Classifier: Programming Language :: Python :: 3    
Classifier: License :: OSI Approved :: MIT License
Classifier: Operating System :: OS Independent
Requires-Python: >=3
Requires-Dist: pandas
